[
    {
        "logo_sponsor": 0,
        "league_id_14": 4579,
        "league_id_1": 3671,
        "url": "twitter.com/OGDota2",
        "league_id_2": 3726,
        "league_id_5": 3902,
        "admin_account_id": 100841499,
        "league_id_6": 4210,
        "league_id_15": 4664,
        "time_created": 1446392040,
        "tag": "OG",
        "player_3_account_id": 19672354,
        "name": "OG Dota2",
        "player_0_account_id": 38628747,
        "logo": 270595013853525356,
        "league_id_3": 3781,
        "country_code": "us",
        "calibration_games_remaining": 3,
        "league_id_12": 4507,
        "league_id_10": 4461,
        "league_id_7": 4266,
        "league_id_4": 3865,
        "league_id_13": 4554,
        "league_id_9": 4442,
        "games_played": 0,
        "player_1_account_id": 94155156,
        "league_id_8": 4301,
        "league_id_11": 4479,
        "league_id_0": 3534,
        "player_2_account_id": 100841499
    },
    {
        "logo_sponsor": 392172445572106348,
        "league_id_41": 1803,
        "league_id_30": 196,
        "league_id_14": 47,
        "league_id_68": 3671,
        "league_id_17": 53,
        "league_id_5": 22,
        "league_id_6": 27,
        "league_id_57": 2661,
        "league_id_45": 2045,
        "league_id_79": 4479,
        "league_id_66": 3502,
        "league_id_23": 104,
        "league_id_26": 110,
        "player_0_account_id": 3916428,
        "league_id_4": 21,
        "league_id_77": 4442,
        "league_id_11": 34,
        "player_5_account_id": 101495620,
        "league_id_29": 124,
        "league_id_13": 46,
        "league_id_62": 2815,
        "league_id_84": 65002,
        "league_id_0": 11,
        "league_id_36": 1068,
        "league_id_69": 3726,
        "league_id_53": 2339,
        "url": "thealliance.gg",
        "league_id_2": 15,
        "league_id_35": 1014,
        "time_created": 1351163475,
        "league_id_48": 2140,
        "league_id_31": 203,
        "league_id_85": 65006,
        "league_id_27": 112,
        "league_id_78": 4461,
        "league_id_67": 3534,
        "league_id_24": 108,
        "league_id_16": 51,
        "league_id_10": 33,
        "player_4_account_id": 76482434,
        "league_id_71": 3798,
        "league_id_82": 4664,
        "league_id_39": 1248,
        "league_id_43": 1936,
        "league_id_9": 32,
        "games_played": 1438,
        "league_id_60": 2733,
        "league_id_38": 1135,
        "league_id_83": 4716,
        "player_2_account_id": 41231571,
        "league_id_63": 2877,
        "league_id_74": 4088,
        "league_id_56": 2470,
        "league_id_34": 600,
        "league_id_80": 4554,
        "tag": "Alliance",
        "player_3_account_id": 41288955,
        "league_id_52": 2337,
        "league_id_32": 223,
        "league_id_3": 20,
        "league_id_28": 114,
        "league_id_50": 2172,
        "league_id_42": 1886,
        "calibration_games_remaining": 3,
        "league_id_58": 2680,
        "league_id_73": 3902,
        "league_id_65": 3092,
        "league_id_64": 2980,
        "league_id_44": 1942,
        "league_id_15": 48,
        "league_id_61": 2790,
        "league_id_51": 2190,
        "league_id_8": 29,
        "league_id_33": 232,
        "league_id_54": 2358,
        "league_id_22": 103,
        "league_id_72": 3865,
        "league_id_40": 1712,
        "league_id_1": 13,
        "league_id_46": 2096,
        "admin_account_id": 32428445,
        "country_code": "se",
        "league_id_49": 2158,
        "league_id_18": 61,
        "league_id_59": 2686,
        "player_1_account_id": 32428445,
        "name": "Alliance",
        "league_id_70": 3781,
        "league_id_20": 70,
        "logo": 392172445572106046,
        "league_id_21": 78,
        "league_id_86": 65013,
        "league_id_81": 4579,
        "league_id_12": 45,
        "league_id_75": 4266,
        "league_id_76": 4289,
        "league_id_7": 28,
        "league_id_55": 2418,
        "league_id_47": 2129,
        "league_id_37": 1123,
        "league_id_19": 69,
        "league_id_25": 109
    },
    {
        "logo_sponsor": 352770370135083122,
        "league_id_22": 4664,
        "league_id_17": 4546,
        "league_id_14": 4405,
        "league_id_1": 1709,
        "league_id_19": 4598,
        "url": "",
        "league_id_2": 1869,
        "league_id_5": 2733,
        "player_4_account_id": 118134220,
        "country_code": "cn",
        "league_id_15": 4442,
        "time_created": 1408948494,
        "tag": "Wings",
        "player_3_account_id": 117990312,
        "name": "the wings gaming",
        "player_0_account_id": 101586543,
        "league_id_23": 4693,
        "admin_account_id": 111114687,
        "logo": 352770708597344369,
        "league_id_18": 4554,
        "league_id_3": 2119,
        "league_id_21": 4660,
        "league_id_6": 3671,
        "league_id_20": 4646,
        "calibration_games_remaining": 3,
        "league_id_12": 4266,
        "league_id_16": 4479,
        "league_id_10": 3904,
        "player_5_account_id": 129585121,
        "league_id_7": 3781,
        "league_id_4": 2339,
        "league_id_13": 4357,
        "league_id_9": 3902,
        "player_6_account_id": 162310729,
        "games_played": 0,
        "player_1_account_id": 102644565,
        "league_id_8": 3877,
        "league_id_11": 4088,
        "league_id_0": 1523,
        "player_2_account_id": 111114687
    },
    {
        "logo_sponsor": 540768028333677405,
        "league_id_14": 2986,
        "league_id_17": 3781,
        "league_id_5": 2140,
        "league_id_6": 2158,
        "tag": "Secret",
        "player_3_account_id": 5390881,
        "league_id_23": 4301,
        "league_id_3": 1942,
        "league_id_28": 4664,
        "league_id_20": 4088,
        "player_0_account_id": 30237211,
        "league_id_29": 4768,
        "league_id_11": 2686,
        "league_id_4": 2129,
        "league_id_13": 2877,
        "league_id_27": 4646,
        "league_id_8": 2392,
        "admin_account_id": 5390881,
        "league_id_22": 4266,
        "league_id_1": 1886,
        "url": "teamsecret.gg",
        "league_id_2": 1936,
        "country_code": "",
        "time_created": 1408993713,
        "name": "Team Secret",
        "calibration_games_remaining": 3,
        "league_id_9": 2418,
        "league_id_26": 4479,
        "logo": 543025270456493033,
        "league_id_21": 4210,
        "league_id_12": 2733,
        "league_id_24": 4357,
        "league_id_16": 3671,
        "league_id_10": 2661,
        "player_4_account_id": 6922000,
        "league_id_7": 2339,
        "league_id_18": 3798,
        "league_id_15": 3502,
        "league_id_0": 1803,
        "games_played": 0,
        "player_1_account_id": 87278757,
        "player_2_account_id": 86745912,
        "league_id_19": 3902,
        "league_id_25": 4461
    },
    {
        "logo_sponsor": 0,
        "league_id_41": 1157,
        "league_id_30": 112,
        "league_id_14": 45,
        "league_id_68": 4210,
        "league_id_17": 50,
        "league_id_5": 12,
        "league_id_6": 13,
        "league_id_57": 2392,
        "league_id_45": 1667,
        "league_id_79": 65005,
        "league_id_66": 3798,
        "league_id_23": 74,
        "league_id_26": 97,
        "player_0_account_id": 23223261,
        "league_id_4": 11,
        "league_id_77": 65001,
        "league_id_11": 32,
        "player_5_account_id": 86727555,
        "league_id_29": 109,
        "league_id_13": 41,
        "league_id_62": 2980,
        "league_id_0": 4,
        "league_id_36": 232,
        "league_id_69": 4266,
        "league_id_53": 2190,
        "url": "www.myeg.net",
        "league_id_2": 7,
        "league_id_35": 223,
        "time_created": 1338981400,
        "league_id_48": 1936,
        "league_id_31": 114,
        "league_id_27": 103,
        "league_id_78": 65002,
        "league_id_67": 3902,
        "league_id_24": 78,
        "league_id_16": 48,
        "league_id_10": 25,
        "player_4_account_id": 111620041,
        "league_id_71": 4301,
        "league_id_39": 1068,
        "league_id_43": 1262,
        "league_id_9": 22,
        "games_played": 1531,
        "league_id_60": 2686,
        "league_id_38": 600,
        "player_2_account_id": 87276347,
        "league_id_63": 3454,
        "league_id_74": 4646,
        "league_id_56": 2363,
        "league_id_34": 184,
        "league_id_80": 65013,
        "tag": "EG",
        "player_3_account_id": 70884685,
        "league_id_52": 2140,
        "league_id_32": 176,
        "league_id_3": 9,
        "league_id_28": 104,
        "league_id_50": 2096,
        "league_id_42": 1248,
        "calibration_games_remaining": 3,
        "league_id_58": 2484,
        "league_id_73": 4479,
        "league_id_65": 3781,
        "league_id_64": 3671,
        "league_id_44": 1663,
        "league_id_15": 47,
        "league_id_61": 2733,
        "league_id_51": 2129,
        "league_id_8": 21,
        "player_6_account_id": 87177591,
        "league_id_33": 181,
        "league_id_54": 2337,
        "league_id_22": 70,
        "league_id_72": 4461,
        "league_id_40": 1135,
        "league_id_1": 6,
        "league_id_46": 1803,
        "admin_account_id": 70884685,
        "country_code": "us",
        "league_id_49": 1942,
        "league_id_18": 51,
        "league_id_59": 2661,
        "player_1_account_id": 73562326,
        "name": "Evil Geniuses",
        "league_id_70": 4289,
        "league_id_20": 57,
        "logo": 491274777986256733,
        "league_id_21": 61,
        "league_id_12": 34,
        "league_id_75": 4664,
        "league_id_76": 4768,
        "league_id_7": 17,
        "league_id_55": 2339,
        "league_id_47": 1886,
        "league_id_37": 235,
        "league_id_19": 53,
        "league_id_25": 92
    },
    {
        "logo_sponsor": 0,
        "league_id_41": 1803,
        "league_id_30": 203,
        "league_id_14": 46,
        "league_id_68": 3902,
        "league_id_17": 53,
        "league_id_5": 18,
        "league_id_6": 20,
        "league_id_57": 2790,
        "league_id_45": 2045,
        "league_id_79": 4646,
        "league_id_66": 3781,
        "league_id_23": 104,
        "league_id_26": 112,
        "player_0_account_id": 89550641,
        "league_id_4": 16,
        "league_id_77": 4554,
        "league_id_11": 32,
        "player_5_account_id": 70388657,
        "league_id_29": 196,
        "league_id_13": 41,
        "league_id_62": 3454,
        "league_id_84": 65013,
        "league_id_0": 4,
        "league_id_36": 1157,
        "league_id_69": 4119,
        "league_id_53": 2661,
        "url": "",
        "league_id_2": 8,
        "league_id_35": 1135,
        "time_created": 1338843412,
        "league_id_48": 2339,
        "league_id_31": 223,
        "league_id_27": 124,
        "league_id_78": 4579,
        "league_id_67": 3798,
        "league_id_24": 106,
        "league_id_16": 51,
        "league_id_10": 29,
        "player_4_account_id": 176184718,
        "league_id_71": 4266,
        "league_id_82": 65002,
        "league_id_39": 1712,
        "league_id_43": 1887,
        "league_id_9": 28,
        "games_played": 977,
        "league_id_60": 3092,
        "league_id_38": 1663,
        "league_id_83": 65006,
        "player_2_account_id": 117421467,
        "league_id_63": 3502,
        "league_id_74": 4461,
        "league_id_56": 2733,
        "league_id_34": 1068,
        "league_id_80": 4664,
        "tag": "Na`Vi",
        "player_3_account_id": 169181898,
        "league_id_52": 2511,
        "league_id_32": 232,
        "league_id_3": 13,
        "league_id_28": 184,
        "league_id_50": 2418,
        "league_id_42": 1886,
        "calibration_games_remaining": 3,
        "league_id_58": 2877,
        "league_id_73": 4442,
        "league_id_65": 3726,
        "league_id_64": 3671,
        "league_id_44": 1936,
        "league_id_15": 48,
        "league_id_61": 3340,
        "league_id_51": 2470,
        "league_id_8": 22,
        "league_id_33": 600,
        "league_id_54": 2680,
        "league_id_22": 103,
        "league_id_72": 4357,
        "league_id_40": 1761,
        "league_id_1": 6,
        "league_id_46": 2140,
        "admin_account_id": 70388657,
        "country_code": "ua",
        "league_id_49": 2358,
        "league_id_18": 54,
        "league_id_59": 2986,
        "player_1_account_id": 89625472,
        "name": "Natus Vincere",
        "league_id_70": 4210,
        "league_id_20": 70,
        "logo": 46499322609643214,
        "league_id_21": 78,
        "league_id_81": 65001,
        "league_id_12": 34,
        "league_id_75": 4479,
        "league_id_76": 4507,
        "league_id_7": 21,
        "league_id_55": 2686,
        "league_id_47": 2158,
        "league_id_37": 1248,
        "league_id_19": 69,
        "league_id_25": 108
    },
    {
        "logo_sponsor": 507027582312707572,
        "league_id_22": 4646,
        "league_id_17": 4357,
        "league_id_14": 4266,
        "league_id_1": 2392,
        "url": "http://digitalchaos.gg",
        "league_id_2": 2747,
        "league_id_5": 3502,
        "player_4_account_id": 87382579,
        "country_code": "us",
        "league_id_15": 4289,
        "time_created": 1440225254,
        "tag": "DC",
        "player_3_account_id": 86725175,
        "name": "Digital Chaos",
        "player_0_account_id": 690740,
        "league_id_23": 4660,
        "admin_account_id": 690740,
        "logo": 692780106202747975,
        "league_id_18": 4442,
        "league_id_3": 3341,
        "league_id_21": 4554,
        "league_id_6": 3671,
        "league_id_20": 4479,
        "calibration_games_remaining": 3,
        "league_id_12": 4181,
        "league_id_24": 4664,
        "league_id_16": 4297,
        "league_id_10": 3960,
        "player_5_account_id": 103735745,
        "league_id_7": 3781,
        "league_id_4": 3454,
        "league_id_13": 4210,
        "league_id_9": 3902,
        "league_id_19": 4461,
        "games_played": 0,
        "player_1_account_id": 84429681,
        "league_id_8": 3798,
        "league_id_11": 4088,
        "league_id_0": 2140,
        "player_2_account_id": 86700461
    },
    {
        "logo_sponsor": 259341780473050520,
        "league_id_17": 4688,
        "league_id_14": 4660,
        "league_id_1": 3454,
        "url": "https://www.facebook.com/ExecrationGG/?fref=ts",
        "league_id_2": 3960,
        "league_id_5": 4266,
        "player_4_account_id": 154715080,
        "country_code": "ph",
        "league_id_15": 4664,
        "time_created": 1446105893,
        "tag": "XctN",
        "player_3_account_id": 91654584,
        "name": "Execration",
        "player_0_account_id": 102099826,
        "admin_account_id": 91654584,
        "logo": 259341780473050115,
        "league_id_3": 4088,
        "league_id_6": 4289,
        "calibration_games_remaining": 3,
        "league_id_12": 4554,
        "league_id_16": 4665,
        "league_id_10": 4479,
        "player_5_account_id": 155494381,
        "league_id_7": 4357,
        "league_id_4": 4122,
        "league_id_13": 4646,
        "league_id_9": 4471,
        "games_played": 0,
        "player_1_account_id": 114980990,
        "league_id_8": 4442,
        "league_id_11": 4515,
        "league_id_0": 2693,
        "player_2_account_id": 152545459
    },
    {
        "league_id_34": 2877,
        "logo_sponsor": 269473510901644183,
        "league_id_41": 3902,
        "league_id_30": 2661,
        "league_id_14": 1524,
        "league_id_2": 197,
        "league_id_5": 1124,
        "league_id_6": 1175,
        "league_id_57": 4700,
        "league_id_49": 4442,
        "league_id_37": 3502,
        "tag": "MVP",
        "league_id_52": 4554,
        "league_id_45": 4210,
        "league_id_32": 2733,
        "league_id_23": 2158,
        "league_id_3": 232,
        "league_id_28": 2392,
        "league_id_50": 4461,
        "league_id_20": 2057,
        "player_0_account_id": 93119769,
        "league_id_29": 2418,
        "league_id_11": 1264,
        "league_id_4": 600,
        "league_id_13": 1350,
        "league_id_27": 2339,
        "league_id_44": 4112,
        "league_id_43": 4088,
        "league_id_51": 4479,
        "league_id_8": 1229,
        "league_id_0": 91,
        "league_id_36": 3454,
        "league_id_33": 2815,
        "league_id_54": 4646,
        "league_id_22": 2079,
        "league_id_17": 1709,
        "league_id_53": 4579,
        "league_id_40": 3798,
        "league_id_1": 125,
        "league_id_55": 4660,
        "url": "MVPPhoenix",
        "league_id_46": 4266,
        "admin_account_id": 93119769,
        "country_code": "kr",
        "league_id_35": 2980,
        "time_created": 1384856202,
        "league_id_48": 4405,
        "league_id_31": 2686,
        "name": "MVP Phoenix",
        "calibration_games_remaining": 3,
        "league_id_9": 1242,
        "league_id_26": 2337,
        "logo": 269473510901644040,
        "league_id_21": 2058,
        "league_id_12": 1301,
        "league_id_24": 2178,
        "league_id_16": 1669,
        "league_id_10": 1248,
        "league_id_56": 4664,
        "league_id_7": 1177,
        "league_id_39": 3781,
        "league_id_18": 1934,
        "league_id_15": 1663,
        "league_id_47": 4357,
        "games_played": 384,
        "player_1_account_id": 112377459,
        "league_id_38": 3671,
        "player_2_account_id": 145550466,
        "league_id_42": 3960,
        "league_id_19": 1936,
        "league_id_25": 2190
    },
    {
        "logo_sponsor": 0,
        "league_id_1": 4461,
        "url": "escape.gg",
        "league_id_2": 4479,
        "league_id_5": 4554,
        "player_4_account_id": 86738694,
        "country_code": "",
        "time_created": 1458588669,
        "tag": "ESC",
        "player_3_account_id": 4281729,
        "name": "Escape Gaming",
        "player_0_account_id": 89117038,
        "admin_account_id": 4281729,
        "logo": 267218287321613843,
        "league_id_3": 4507,
        "league_id_6": 4646,
        "calibration_games_remaining": 3,
        "league_id_7": 4660,
        "league_id_4": 4525,
        "league_id_9": 4716,
        "games_played": 0,
        "player_1_account_id": 100317750,
        "league_id_8": 4664,
        "league_id_0": 4442,
        "player_2_account_id": 169025618
    },
    {
        "league_id_34": 1248,
        "logo_sponsor": 0,
        "league_id_41": 3781,
        "league_id_30": 1100,
        "league_id_14": 74,
        "league_id_47": 4289,
        "league_id_17": 104,
        "league_id_5": 29,
        "league_id_6": 32,
        "league_id_49": 4442,
        "league_id_37": 3502,
        "tag": "Liquid",
        "player_3_account_id": 82262664,
        "league_id_52": 4554,
        "league_id_45": 4210,
        "league_id_32": 1135,
        "league_id_23": 184,
        "league_id_3": 27,
        "league_id_28": 235,
        "league_id_50": 4461,
        "league_id_20": 112,
        "player_0_account_id": 26771994,
        "league_id_29": 600,
        "league_id_11": 50,
        "player_5_account_id": 113439358,
        "league_id_4": 28,
        "league_id_13": 53,
        "league_id_27": 232,
        "league_id_44": 4088,
        "league_id_43": 3960,
        "league_id_51": 4479,
        "league_id_8": 34,
        "admin_account_id": 113439358,
        "league_id_36": 3454,
        "league_id_33": 1157,
        "league_id_54": 4716,
        "league_id_22": 181,
        "league_id_53": 4664,
        "league_id_40": 3726,
        "league_id_1": 22,
        "league_id_55": 65006,
        "url": "www.teamliquidpro.com/",
        "league_id_46": 4266,
        "league_id_2": 25,
        "country_code": "",
        "league_id_35": 1709,
        "time_created": 1349400722,
        "league_id_48": 4357,
        "league_id_31": 1127,
        "name": "Team Liquid",
        "calibration_games_remaining": 3,
        "league_id_9": 41,
        "league_id_26": 223,
        "logo": 451783905032671206,
        "league_id_21": 167,
        "league_id_56": 65013,
        "league_id_12": 51,
        "league_id_24": 196,
        "league_id_16": 103,
        "league_id_10": 48,
        "player_4_account_id": 86799300,
        "league_id_7": 33,
        "league_id_39": 3671,
        "league_id_18": 108,
        "league_id_15": 78,
        "league_id_0": 21,
        "games_played": 1506,
        "player_1_account_id": 34505203,
        "league_id_38": 3534,
        "player_2_account_id": 72312627,
        "league_id_42": 3902,
        "league_id_19": 110,
        "league_id_25": 203
    },
    {
        "league_id_34": 2912,
        "logo_sponsor": 262714246038194422,
        "league_id_41": 3877,
        "league_id_30": 2686,
        "league_id_14": 1663,
        "league_id_47": 4461,
        "league_id_17": 1803,
        "league_id_5": 1097,
        "league_id_6": 1116,
        "league_id_49": 4525,
        "league_id_37": 3502,
        "tag": "Newbee",
        "player_3_account_id": 87012746,
        "league_id_52": 4646,
        "league_id_45": 4405,
        "league_id_0": 177,
        "league_id_23": 2057,
        "league_id_3": 600,
        "league_id_28": 2418,
        "league_id_50": 4546,
        "league_id_20": 1936,
        "player_0_account_id": 113175114,
        "league_id_29": 2661,
        "league_id_11": 1418,
        "player_5_account_id": 88553213,
        "league_id_4": 1014,
        "league_id_13": 1523,
        "league_id_27": 2358,
        "league_id_44": 4301,
        "league_id_43": 4266,
        "league_id_51": 4598,
        "league_id_8": 1284,
        "admin_account_id": 197534213,
        "league_id_36": 2986,
        "league_id_33": 2877,
        "league_id_54": 4664,
        "league_id_22": 2045,
        "league_id_53": 4660,
        "league_id_40": 3798,
        "league_id_1": 189,
        "league_id_55": 4693,
        "url": "http://t.qq.com/NBgaming",
        "league_id_46": 4442,
        "league_id_2": 232,
        "country_code": "cn",
        "league_id_35": 2922,
        "time_created": 1393518254,
        "league_id_48": 4479,
        "league_id_26": 2339,
        "league_id_31": 2733,
        "name": "Newbee",
        "calibration_games_remaining": 3,
        "league_id_9": 1350,
        "player_4_account_id": 88508515,
        "logo": 262714246038194128,
        "league_id_21": 2032,
        "league_id_12": 1448,
        "league_id_24": 2079,
        "league_id_16": 1761,
        "league_id_10": 1407,
        "league_id_32": 2815,
        "league_id_7": 1157,
        "league_id_39": 3781,
        "league_id_18": 1886,
        "league_id_15": 1709,
        "player_6_account_id": 89157606,
        "games_played": 362,
        "player_1_account_id": 139876032,
        "league_id_38": 3671,
        "player_2_account_id": 197534213,
        "league_id_42": 4039,
        "league_id_19": 1934,
        "league_id_25": 2178
    },
    {
        "league_id_34": 4693,
        "logo_sponsor": 263843003896036281,
        "league_id_30": 4598,
        "league_id_14": 2985,
        "league_id_17": 3671,
        "league_id_5": 2358,
        "league_id_6": 2418,
        "tag": "EHOME",
        "player_3_account_id": 163227125,
        "league_id_32": 4660,
        "league_id_23": 4301,
        "league_id_3": 2032,
        "league_id_28": 4546,
        "league_id_20": 3877,
        "player_0_account_id": 134276083,
        "league_id_29": 4554,
        "league_id_11": 2877,
        "league_id_4": 2339,
        "league_id_13": 2922,
        "league_id_27": 4479,
        "league_id_8": 2686,
        "admin_account_id": 163227125,
        "league_id_33": 4664,
        "league_id_22": 4266,
        "league_id_1": 7,
        "url": "",
        "league_id_2": 10,
        "country_code": "cn",
        "league_id_35": 65001,
        "time_created": 1338330584,
        "league_id_31": 4646,
        "name": "EHOME",
        "calibration_games_remaining": 3,
        "league_id_9": 2733,
        "league_id_26": 4461,
        "logo": 263843003896035882,
        "league_id_21": 3902,
        "league_id_12": 2912,
        "league_id_24": 4357,
        "league_id_16": 3502,
        "league_id_10": 2815,
        "player_4_account_id": 89423756,
        "league_id_7": 2661,
        "league_id_18": 3781,
        "league_id_15": 2986,
        "league_id_0": 5,
        "games_played": 0,
        "player_1_account_id": 109758944,
        "player_2_account_id": 135878232,
        "league_id_19": 3798,
        "league_id_25": 4442
    },
    {
        "logo_sponsor": 307739466827820146,
        "league_id_41": 1135,
        "league_id_30": 181,
        "league_id_14": 57,
        "league_id_68": 4442,
        "league_id_17": 78,
        "league_id_5": 32,
        "league_id_6": 33,
        "league_id_57": 3454,
        "league_id_45": 1761,
        "league_id_66": 4266,
        "league_id_23": 110,
        "league_id_26": 124,
        "player_0_account_id": 89871557,
        "league_id_4": 29,
        "league_id_11": 48,
        "player_5_account_id": 66189266,
        "league_id_29": 176,
        "league_id_13": 53,
        "league_id_62": 3902,
        "league_id_0": 21,
        "league_id_36": 600,
        "league_id_69": 4461,
        "league_id_53": 2680,
        "url": "www.fnatic.com",
        "league_id_2": 27,
        "league_id_35": 232,
        "time_created": 1360862037,
        "league_id_48": 1936,
        "league_id_31": 184,
        "league_id_27": 161,
        "league_id_67": 4357,
        "league_id_24": 112,
        "league_id_16": 70,
        "league_id_10": 47,
        "player_4_account_id": 116585378,
        "league_id_71": 4479,
        "league_id_39": 1123,
        "league_id_43": 1248,
        "league_id_9": 46,
        "games_played": 1298,
        "league_id_60": 3781,
        "league_id_38": 1068,
        "player_2_account_id": 102099826,
        "league_id_63": 3960,
        "league_id_74": 4664,
        "league_id_56": 2980,
        "league_id_34": 223,
        "tag": "Fnatic",
        "player_3_account_id": 111034589,
        "league_id_52": 2363,
        "league_id_32": 196,
        "league_id_3": 28,
        "league_id_28": 167,
        "league_id_50": 2051,
        "league_id_42": 1157,
        "calibration_games_remaining": 3,
        "league_id_58": 3502,
        "league_id_73": 4646,
        "league_id_65": 4210,
        "league_id_64": 4088,
        "league_id_44": 1712,
        "league_id_15": 69,
        "league_id_61": 3798,
        "league_id_51": 2140,
        "league_id_8": 45,
        "league_id_33": 203,
        "league_id_54": 2686,
        "league_id_22": 109,
        "league_id_72": 4554,
        "league_id_40": 1127,
        "league_id_1": 22,
        "league_id_46": 1803,
        "admin_account_id": 66189266,
        "country_code": "",
        "league_id_49": 1942,
        "league_id_18": 92,
        "league_id_59": 3671,
        "player_1_account_id": 93616251,
        "name": "Fnatic",
        "league_id_70": 4471,
        "league_id_20": 103,
        "logo": 307739466828348574,
        "league_id_21": 104,
        "league_id_12": 51,
        "league_id_75": 65006,
        "league_id_76": 65013,
        "league_id_7": 34,
        "league_id_55": 2733,
        "league_id_47": 1886,
        "league_id_37": 1014,
        "league_id_19": 97,
        "league_id_25": 114
    },
    {
        "logo_sponsor": 275101922741544368,
        "league_id_41": 2032,
        "league_id_30": 1418,
        "league_id_14": 104,
        "league_id_68": 4177,
        "league_id_17": 177,
        "league_id_5": 24,
        "league_id_6": 34,
        "league_id_57": 2985,
        "league_id_45": 2178,
        "league_id_79": 4579,
        "league_id_66": 4039,
        "league_id_23": 1116,
        "league_id_87": 65008,
        "league_id_26": 1248,
        "player_0_account_id": 89217927,
        "league_id_4": 23,
        "league_id_77": 4546,
        "league_id_11": 76,
        "player_5_account_id": 118678359,
        "league_id_29": 1407,
        "league_id_13": 91,
        "league_id_62": 3781,
        "league_id_84": 65001,
        "league_id_0": 5,
        "league_id_36": 1803,
        "league_id_69": 4266,
        "league_id_53": 2815,
        "url": "",
        "league_id_2": 14,
        "league_id_35": 1761,
        "time_created": 1338727837,
        "league_id_48": 2392,
        "league_id_31": 1523,
        "league_id_85": 65004,
        "league_id_27": 1284,
        "league_id_78": 4554,
        "league_id_67": 4088,
        "league_id_24": 1157,
        "league_id_16": 120,
        "league_id_10": 68,
        "player_4_account_id": 106863163,
        "league_id_71": 4357,
        "league_id_82": 4664,
        "league_id_39": 1934,
        "league_id_43": 2096,
        "league_id_9": 54,
        "games_played": 1400,
        "league_id_60": 3671,
        "league_id_38": 1886,
        "league_id_83": 4693,
        "player_2_account_id": 89598554,
        "league_id_63": 3798,
        "league_id_74": 4461,
        "league_id_56": 2922,
        "league_id_34": 1709,
        "league_id_80": 4646,
        "tag": "LGD",
        "player_3_account_id": 98887913,
        "league_id_52": 2733,
        "league_id_32": 1524,
        "league_id_3": 17,
        "league_id_28": 1350,
        "league_id_50": 2661,
        "league_id_42": 2045,
        "calibration_games_remaining": 3,
        "league_id_58": 2986,
        "league_id_73": 4442,
        "league_id_65": 3902,
        "league_id_64": 3877,
        "league_id_44": 2158,
        "league_id_15": 114,
        "league_id_61": 3706,
        "league_id_51": 2686,
        "league_id_8": 52,
        "league_id_33": 1663,
        "league_id_54": 2877,
        "league_id_22": 1097,
        "league_id_72": 4405,
        "league_id_40": 1936,
        "league_id_1": 7,
        "league_id_46": 2339,
        "admin_account_id": 118678359,
        "country_code": "cn",
        "league_id_49": 2418,
        "league_id_18": 189,
        "league_id_59": 3502,
        "player_1_account_id": 89407113,
        "name": "LGD-GAMING",
        "league_id_70": 4301,
        "league_id_20": 600,
        "logo": 275101922741543975,
        "league_id_21": 1014,
        "league_id_86": 65006,
        "league_id_81": 4660,
        "league_id_12": 81,
        "league_id_75": 4479,
        "league_id_76": 4525,
        "league_id_7": 42,
        "league_id_55": 2912,
        "league_id_47": 2358,
        "league_id_37": 1869,
        "league_id_19": 232,
        "league_id_25": 1245
    },
    {
        "logo_sponsor": 262717915353277000,
        "league_id_1": 4405,
        "url": "",
        "league_id_2": 4442,
        "league_id_5": 4525,
        "player_4_account_id": 128513043,
        "country_code": "cn",
        "time_created": 1458189468,
        "tag": "VG.R",
        "player_3_account_id": 114239371,
        "name": "Vici_Gaming Reborn",
        "player_0_account_id": 80929738,
        "admin_account_id": 128513043,
        "logo": 262717915353276756,
        "league_id_3": 4461,
        "league_id_6": 4546,
        "calibration_games_remaining": 3,
        "league_id_12": 4664,
        "league_id_10": 4646,
        "player_5_account_id": 139280377,
        "league_id_7": 4554,
        "league_id_4": 4479,
        "league_id_13": 4693,
        "league_id_9": 4598,
        "player_6_account_id": 139937922,
        "games_played": 0,
        "player_1_account_id": 101695162,
        "league_id_8": 4579,
        "league_id_11": 4660,
        "league_id_0": 4357,
        "player_2_account_id": 108484186
    },
    {
        "logo_sponsor": 379784372242560156,
        "league_id_14": 3960,
        "league_id_17": 4357,
        "league_id_5": 3232,
        "league_id_6": 3454,
        "tag": "TNC",
        "player_3_account_id": 184950344,
        "league_id_23": 4515,
        "league_id_3": 2763,
        "league_id_28": 4664,
        "league_id_20": 4461,
        "player_0_account_id": 167727238,
        "league_id_29": 4768,
        "league_id_11": 3781,
        "league_id_4": 2770,
        "league_id_13": 3902,
        "league_id_27": 4660,
        "league_id_8": 3552,
        "admin_account_id": 167727238,
        "league_id_22": 4479,
        "league_id_1": 2718,
        "url": "https://www.facebook.com/pages/TNC-Pro-Team-Dota2/840515722697409",
        "league_id_2": 2733,
        "country_code": "ph",
        "time_created": 1421144109,
        "name": "TNC Pro Team",
        "calibration_games_remaining": 3,
        "league_id_9": 3570,
        "league_id_26": 4649,
        "logo": 695031906008935467,
        "league_id_21": 4471,
        "league_id_12": 3798,
        "league_id_24": 4554,
        "league_id_16": 4266,
        "league_id_10": 3671,
        "player_4_account_id": 187619311,
        "league_id_7": 3502,
        "league_id_18": 4405,
        "league_id_15": 4088,
        "league_id_0": 2693,
        "games_played": 7,
        "player_1_account_id": 85805514,
        "player_2_account_id": 132309493,
        "league_id_19": 4442,
        "league_id_25": 4646
    },
    {
        "league_id_34": 2854,
        "logo_sponsor": 0,
        "league_id_41": 3781,
        "league_id_30": 2733,
        "league_id_14": 2129,
        "league_id_47": 4289,
        "league_id_17": 2172,
        "league_id_5": 1761,
        "league_id_6": 1800,
        "league_id_57": 4664,
        "league_id_49": 4301,
        "league_id_37": 3341,
        "tag": "coL",
        "player_3_account_id": 49317728,
        "league_id_52": 4461,
        "league_id_45": 4210,
        "league_id_32": 2790,
        "league_id_23": 2418,
        "league_id_3": 1244,
        "league_id_28": 2673,
        "league_id_50": 4357,
        "league_id_20": 2363,
        "player_0_account_id": 12231202,
        "league_id_58": 65001,
        "league_id_29": 2679,
        "league_id_11": 1942,
        "player_5_account_id": 172424257,
        "league_id_4": 1493,
        "league_id_13": 2126,
        "league_id_27": 2661,
        "league_id_44": 4112,
        "league_id_43": 3902,
        "league_id_51": 4442,
        "league_id_8": 1886,
        "admin_account_id": 28291366,
        "league_id_36": 3092,
        "league_id_33": 2815,
        "league_id_54": 4554,
        "league_id_22": 2392,
        "league_id_53": 4479,
        "league_id_40": 3779,
        "league_id_1": 7,
        "league_id_55": 4580,
        "url": "http://compLexityGaming.com",
        "league_id_46": 4266,
        "league_id_2": 9,
        "country_code": "us",
        "league_id_35": 2877,
        "time_created": 1338330535,
        "league_id_48": 4297,
        "league_id_31": 2747,
        "name": "compLexity Gaming",
        "calibration_games_remaining": 3,
        "league_id_9": 1934,
        "league_id_26": 2517,
        "logo": 493527484478845735,
        "league_id_21": 2377,
        "league_id_56": 4646,
        "league_id_12": 1980,
        "league_id_24": 2484,
        "league_id_16": 2158,
        "league_id_10": 1936,
        "player_4_account_id": 50828662,
        "league_id_7": 1829,
        "league_id_39": 3671,
        "league_id_18": 2337,
        "league_id_15": 2140,
        "league_id_0": 4,
        "games_played": 2,
        "player_1_account_id": 18180970,
        "league_id_38": 3534,
        "player_2_account_id": 28291366,
        "league_id_42": 3798,
        "league_id_19": 2339,
        "league_id_25": 2511
    }
]